{
  "source": "cipher",
  "type": "user-action",
  "data": {
    "action": "songsterr-hook-pattern",
    "context": {
      "result": "success",
      "context": {
        "patternId": "hook-1755472051460-6waovn1fq",
        "complexity": 1,
        "tags": [
          "songsterr",
          "training",
          "hook",
          "audio",
          "playback"
        ],
        "confidence": 0.85,
        "dependencies": [],
        "sourceFile": "/Users/brettbolzenthal/Desktop/maestro-ai/cipher-engine-clean-v2/ai-team-input/songsterr-content.txt",
        "handlerName": "DigestAndLearn"
      }
    },
    "timestamp": 1755472052583,
    "frequency": 1
  },
  "timestamp": 1755472052583,
  "musicApp": true,
  "dualBrainActive": false
}