{
  "source": "cipher",
  "type": "user-action",
  "data": {
    "action": "file-analysis-success",
    "context": {
      "result": "success",
      "context": {
        "handlerName": "showRouteTreeHandler",
        "version": "v20-LIGHTWEIGHT",
        "filePath": "/Users/brettbolzenthal/Desktop/maestro-ai/ava/tsconfig.json",
        "fileName": "tsconfig.json",
        "extension": ".json",
        "contentLength": 577,
        "pattern": "healthy-file"
      }
    },
    "timestamp": 1755738057866,
    "frequency": 1
  },
  "timestamp": 1755738057866,
  "musicApp": true,
  "dualBrainActive": false
}